{
    "characters": [
        47579,
        47579,
        42973,
        42973,
        49279,
        49279,
        47839,
        47839,
        47581,
        47581,
        47583,
        47583,
        49277,
        49277,
        49281,
        49281,
        47587,
        47587,
        49271,
        49271,
        49285,
        49285,
        75902,
        75902,
        47585,
        47585,
        49273,
        49273,
        48333,
        48333,
        47841,
        47841,
        49299,
        49299,
        49269,
        49269
    ],
    "episodes": 1,
    "id": "10714",
    "picture": "http://cdn.myanimelist.net/images/anime/7/32945.jpg",
    "released": "2011-08-13T03:00:00.000Z",
    "synopsis": "The story follows a boy named Quon and others who suddenly wake up with supernatural powers.",
    "tags": [
        "supernatural"
    ],
    "title": "Towa no Quon 3: Mugen no Renza",
    "title_en": "Towanoquon: The Complicity of Dreams",
    "title_jp": "トワノクオン 第３章 夢幻の連座",
    "type": "Movie"
}