{
    "id": 12859,
    "title": "One Piece Film: Z",
    "title_en": "One Piece Film Z",
    "title_jp": "ワンピース　フィルム　﻿Ｚ",
    "picture": "http://cdn.myanimelist.net/images/anime/6/44297.jpg",
    "synopsis": "Zephyr, now known as Z, rides the seas with only one goal: Destroy all pirates and their dreams at becoming King of Pirates. When Luffy and his crew encounter him at sea, not only are they utterly defeated by the man with an arm made of Seastone, Nami, Robin, Brook, and Chopper are turned 10 years younger due to Z's minion Ain. Luffy is so determined to win against him that he does not even notice Z's master plan that could sacrifice thousands of lives.",
    "type": "Movie",
    "episodes": 1,
    "tags": [
        "action",
        "adventure",
        "comedy",
        "drama",
        "fantasy",
        "shounen"
    ],
    "released": "2012-12-15T02:00:00.000Z",
    "characters": [
        5627,
        64,
        40,
        723,
        61,
        62,
        305,
        309,
        724,
        69067,
        67143,
        67141,
        21093,
        12361,
        89823,
        12362,
        90305,
        2752,
        122393,
        90307,
        8064,
        22687,
        13018,
        21558
    ]
}