{
    "id": 1425,
    "title": "Lupin III: Part II",
    "title_en": null,
    "title_jp": "新・ルパン三世",
    "picture": "http://cdn.myanimelist.net/images/anime/7/34035.jpg",
    "synopsis": "Lupin III chronicles the adventures of Arsene Lupin III, the world's greatest thief, and his partners in crime: master marksman Daisuke Jigen, beautiful and scheming Fujiko Mine and stoic samurai Goemon Ishikawa XIII. Lupin and his gang travel around the globe in search of the world's greatest treasures and riches and always keeping one step ahead of the tireless Inspector Zenigata, who has vowed to bring Lupin to justice. ",
    "type": "TV",
    "episodes": 155,
    "tags": [
        "action",
        "adventure",
        "comedy",
        "shounen"
    ],
    "released": "1977-10-03T03:00:00.000Z",
    "characters": [
        1046,
        1045,
        1044,
        1047,
        123846,
        1048,
        116427,
        117041,
        116155,
        117695,
        117829,
        117355,
        116541,
        115853,
        116141,
        117709,
        117959,
        123849,
        117371,
        116859,
        116459,
        117579,
        117213,
        117189,
        117045,
        118115,
        116561,
        116555,
        116051,
        117481,
        117859,
        117975,
        116045,
        117967,
        117969,
        117701,
        116861,
        117357,
        117825,
        117687,
        115995,
        117205,
        116563,
        117093,
        123842,
        123841,
        117569,
        117515,
        117697,
        117335,
        116807,
        116381,
        117855,
        116839,
        117479,
        117965,
        117333,
        118121,
        117499,
        117497,
        116811,
        117951,
        118043,
        118039,
        116391,
        117349,
        117585,
        116049,
        117939,
        117941,
        117191,
        117203,
        117097,
        117853,
        118037,
        116853,
        117351,
        116151,
        115849,
        117365,
        118063,
        116867,
        117491,
        118051,
        115997,
        116849,
        116147,
        118131,
        117971,
        116149,
        117955,
        118125,
        116461,
        117857,
        117847,
        116047,
        116565,
        117957,
        117945,
        116455,
        118127,
        118055,
        117827,
        118133,
        117363,
        117101,
        115795,
        117621,
        116539,
        117343,
        117193,
        117565,
        117849,
        117851,
        116823,
        117347,
        117353,
        116379,
        118123,
        117691,
        117693,
        118053,
        116845,
        116389,
        117713,
        116817,
        117577,
        116055,
        117699,
        117843,
        116451,
        116387,
        117961,
        116399,
        118041,
        116145,
        117581,
        117689,
        117711,
        117503,
        116809,
        116855,
        116433,
        116377,
        116841,
        116857,
        117837,
        60235,
        116557,
        117505,
        117489,
        117207,
        117209,
        117575,
        116393,
        118129,
        117195,
        117215,
        116385,
        116395,
        116821,
        117185,
        118119,
        117083,
        116805,
        116143,
        117477,
        117197,
        117721,
        116813,
        123848,
        117219,
        116835,
        117373,
        117935,
        117937,
        117977,
        116543,
        123843,
        117095,
        116153,
        117683,
        116431,
        117963,
        117979,
        117085,
        117949,
        117501,
        117487,
        117361,
        117685,
        115851,
        117513,
        116383,
        118111,
        117571,
        117033,
        117931,
        118061,
        117845,
        116851,
        118059,
        117617,
        117703,
        117619,
        118117,
        116843,
        117599,
        117047,
        118057,
        118049,
        94589,
        115999,
        116423,
        117953,
        117199,
        117043,
        116457,
        117727,
        118113,
        118045,
        117217,
        116833,
        117367,
        117601,
        118135,
        115797,
        117927,
        117211,
        76790,
        117567,
        117027,
        117359,
        116825,
        117929,
        117563,
        116837,
        117495,
        117729,
        117049,
        117925,
        116397,
        116549,
        117341,
        117337,
        117339,
        117089,
        116819,
        117587,
        123850,
        117507,
        117201,
        118109,
        117707,
        117841,
        117943,
        117087,
        76796,
        117511,
        116865,
        117091,
        117375,
        117973,
        117483,
        117031,
        117485,
        118035,
        117593,
        123845,
        117573,
        117597,
        115847,
        117037,
        117623,
        117493,
        117933,
        116559,
        117369,
        123851,
        117099,
        116551,
        117345,
        116815,
        117589,
        117591,
        116553,
        116429,
        117377,
        123844,
        117611,
        117705,
        117823,
        116425,
        117509,
        117839,
        117187,
        116863,
        117613,
        117615,
        116869,
        117583
    ]
}