{
    "id": 14811,
    "title": "GJ-bu",
    "title_en": "GJ Club",
    "title_jp": "GJ部",
    "picture": "http://cdn.myanimelist.net/images/anime/10/45995.jpg",
    "synopsis": "Shinomiya Kyouya is forced to become a new member of the GJ, an unidentified club that dwells in a room of the former building of a certain school. Here he meets the club leader, Mao, a short girl with a big attitude; Mao's younger sister, Megumi, who has the heart of a bipolar angel; the recognized genius with a lack of common sense, Shion; and the always-hungry and mysterious Kirara. Time flies with these unique girls around. ",
    "type": "TV",
    "episodes": 12,
    "tags": [
        "comedy",
        "school",
        "slice_of_life"
    ],
    "released": "2013-01-10T02:00:00.000Z",
    "characters": [
        74081,
        74079,
        74087,
        76999,
        74085,
        74083,
        76993,
        81431,
        76995,
        76991,
        76997,
        81433
    ]
}