{
    "id": 15307,
    "title": "Smile Precure! Movie: Ehon no Naka wa Minna Chiguhagu!",
    "title_en": null,
    "title_jp": "映画 スマイルプリキュア! 絵本の中はみんなチグハグ!",
    "picture": "http://cdn.myanimelist.net/images/anime/6/42291.jpg",
    "synopsis": "The movie transports the Precure into a world inside a picture book, where they are guided by Nico, a mysterious inhabitant of the picture book world.",
    "type": "Movie",
    "episodes": 1,
    "tags": [
        "fantasy",
        "kids",
        "magic",
        "shoujo"
    ],
    "released": "2012-10-27T02:00:00.000Z",
    "characters": [
        54017,
        53727,
        101589,
        53671,
        54009,
        53673,
        53677,
        70003,
        101541,
        101577,
        101555,
        101545,
        101547,
        101585,
        101539,
        101559,
        101537,
        101549,
        101583,
        101587,
        101575,
        101569,
        101581,
        101579
    ]
}