{
    "id": 154,
    "title": "Shaman King",
    "title_en": "Shaman King",
    "title_jp": "シャーマンキング",
    "picture": "http://cdn.myanimelist.net/images/anime/4/18990.jpg",
    "synopsis": "A battle is about to begin in Tokyo: the Shaman Fight, a tournament held every five hundred years where shaman—those who can command spirits—confront each other in combat. The victor of this contest becomes the Shaman King and the only one who is able to contact and control the Great Spirit, allowing them to reshape the world as they please through its immense power.",
    "type": "TV",
    "episodes": 64,
    "tags": [
        "action",
        "adventure",
        "comedy",
        "drama",
        "shounen",
        "supernatural"
    ],
    "released": "2001-07-04T03:00:00.000Z",
    "characters": [
        169,
        167,
        172,
        170,
        174,
        171,
        37012,
        20829,
        38760,
        34029,
        61457,
        33416,
        20241,
        20408,
        20856,
        35167,
        20245,
        17219,
        20694,
        29161,
        1529,
        20883,
        18342,
        20419,
        3262,
        35349,
        29629,
        20879,
        101813,
        7137,
        20882,
        101819,
        20242,
        7144,
        20855,
        20421,
        20418,
        20407,
        15349,
        20696,
        20880,
        20406,
        20420,
        20409,
        9147,
        20881,
        7147,
        20240,
        16145,
        30836,
        21129,
        20244,
        19677,
        7145,
        20857,
        6195,
        20884,
        45007,
        45005,
        4327,
        9148,
        12677,
        15558,
        173
    ]
}