{
    "id": 16123,
    "title": "Saki Zenkoku-hen",
    "title_en": "Saki: The Nationals",
    "title_jp": "咲-Saki-全国編",
    "picture": "http://cdn.myanimelist.net/images/anime/12/57979.jpg",
    "synopsis": "Sequel to the Saki series covering the Inter High School Mahjong Championships.",
    "type": "TV",
    "episodes": 13,
    "tags": [
        "game",
        "school",
        "slice_of_life"
    ],
    "released": "2014-01-06T02:00:00.000Z",
    "characters": [
        17275,
        17276,
        17274,
        17279,
        17277,
        17278,
        48499,
        48721,
        18302,
        48731,
        50019,
        48713,
        48715,
        48489,
        23046,
        48647,
        24467,
        56655,
        18297,
        48565,
        60329,
        24455,
        56663,
        93173,
        51847,
        48629,
        22088,
        18303,
        48623,
        115773,
        48561,
        67687,
        23040,
        48727,
        23042,
        48627,
        99667,
        48563,
        48723,
        48619,
        48733,
        18306,
        48711,
        48495,
        48487,
        51849,
        24468,
        69261,
        76534,
        75182,
        48609,
        48803,
        48767,
        75180,
        48637,
        48621,
        18307,
        48493,
        73169,
        99665,
        18305,
        22721,
        60321,
        48719,
        80325,
        48485,
        48625,
        98749,
        23036,
        48641,
        64413,
        23043,
        48709,
        48729,
        46513,
        48725,
        48769,
        23044,
        25830
    ]
}