{
    "id": 1735,
    "title": "Naruto: Shippuuden",
    "title_en": "Naruto: Shippuden",
    "title_jp": "ナルト- 疾風伝",
    "picture": "http://cdn.myanimelist.net/images/anime/5/17407.jpg",
    "type": "TV",
    "episodes": 0,
    "tags": [
        "action",
        "comedy",
        "martial_arts",
        "shounen",
        "super_power"
    ],
    "released": "2007-02-15T02:00:00.000Z",
    "characters": [
        145,
        85,
        13,
        17,
        22894,
        93639,
        93637,
        65133,
        23647,
        44981,
        10697,
        3428,
        130361,
        30190,
        4799,
        20645,
        23473,
        64461,
        10699,
        77435,
        2008,
        94811,
        127095,
        23420,
        66541,
        17310,
        84625,
        41208,
        15081,
        22896,
        52031,
        23008,
        30189,
        34075,
        139847,
        77433,
        93635,
        84623,
        15365,
        12676,
        84621,
        23418,
        57881,
        97793,
        62631,
        30188,
        70989,
        100275,
        97791,
        23476,
        1902,
        34114,
        94985,
        94973,
        77437,
        10791,
        31825,
        95091,
        30185,
        15757,
        33618,
        33619,
        24486,
        13929,
        38643,
        63209,
        23220,
        20741,
        126085,
        94979,
        1662,
        4223,
        78095,
        26933,
        16999,
        30924,
        16952,
        38453,
        62633,
        62129,
        50545,
        63793,
        7738,
        48839,
        65141,
        33791,
        20013,
        23569,
        55293,
        16304,
        2039,
        23223,
        40418,
        23055,
        67287,
        67289,
        31268,
        20894,
        97797,
        50555,
        2792,
        94817,
        34115,
        103823,
        23053,
        50459,
        50553,
        1903,
        62775,
        65135,
        2672,
        30084,
        22898,
        1694,
        1555,
        12563,
        60107,
        15039,
        119785,
        62635,
        22988,
        22880,
        52029,
        21365,
        15073,
        3495,
        15074,
        97781,
        38454,
        63211,
        93633,
        57873,
        97785,
        62637,
        31829,
        63973,
        41209,
        23080,
        2423,
        8495,
        31828,
        3152,
        22996,
        23152,
        3178,
        14032,
        38460,
        39570,
        39606,
        4694,
        94813,
        3151,
        133890,
        22874,
        22248,
        38459,
        22876,
        7608,
        94821,
        8497,
        33792,
        33790,
        18473,
        3438,
        65139,
        9244,
        62639,
        15364,
        62641,
        57879,
        52959,
        88301,
        3179,
        38458,
        34172,
        7407,
        64455,
        23474,
        38455,
        100273,
        94983,
        66547,
        48837,
        66549,
        67281,
        97789,
        67283,
        66543,
        306,
        94975,
        41210,
        33736,
        64447,
        37929,
        39604,
        57871,
        7310,
        23830,
        307,
        103209,
        94977,
        809,
        22648,
        13454,
        728,
        94807,
        22923,
        54685,
        23054,
        64457,
        95093,
        64453,
        122169,
        53251,
        41211,
        17298,
        2535,
        30187,
        2007,
        64449,
        18056,
        22247,
        98659,
        22884,
        23149,
        40689,
        94815,
        15362,
        14082,
        95095,
        33793,
        94819,
        67285,
        22872,
        23475,
        127264,
        108297,
        127263,
        57883,
        2455,
        97795,
        3180,
        2766,
        63791,
        73781,
        60105,
        22920,
        93629,
        64459,
        22184,
        23221,
        94809,
        41212,
        41213,
        98655,
        1901,
        57875,
        8760,
        22873,
        27251,
        31831,
        7571,
        4775,
        3889,
        56693,
        1900,
        23139,
        12465,
        12464,
        109569,
        109567,
        134165,
        93631,
        46605,
        22000,
        23477,
        24487,
        23424,
        22817,
        50461,
        124066,
        39605,
        30427,
        3735,
        77005,
        52053,
        4643,
        38456,
        98657,
        97783,
        57877,
        13483,
        94981,
        41214,
        52051,
        40785,
        63979,
        88307,
        39571,
        23154,
        23151,
        56689,
        23150,
        97787,
        62643,
        39572,
        23759,
        84619,
        3052,
        17197,
        2174,
        60103,
        3710,
        23478,
        17312,
        3149,
        52055,
        30186,
        94987,
        90849,
        22905,
        95097,
        41215,
        19253,
        38461,
        2767,
        15077,
        31269,
        22889,
        98663,
        2910,
        98661,
        63189,
        22908,
        139848,
        22893,
        22891,
        109565,
        94785,
        94735,
        16406,
        14,
        16973,
        53901,
        21122,
        23052,
        41366,
        56697,
        56699,
        2011,
        77441,
        96721,
        22907,
        23219,
        22649,
        15045,
        7302,
        56691,
        77443,
        23222,
        23050,
        31830,
        93627,
        2405,
        64451,
        15072,
        40403,
        77439,
        2009,
        17553,
        2006,
        38457,
        13017,
        97779,
        39573,
        84627,
        97799,
        62645,
        20621,
        102031,
        94823,
        23057,
        56695,
        4773,
        31818,
        49681,
        62647,
        3150,
        22931
    ]
}