{
    "id": 1910,
    "title": "Master Keaton OVA",
    "title_en": null,
    "title_jp": "マスターキートン",
    "picture": "http://cdn.myanimelist.net/images/anime/9/14522.jpg",
    "synopsis": "Taichi Keaton is a man of many talents: father, historian, frequent traveler, negotiator, archaeologist, former survival instructor, and all while working as an insurance investigator for Lloyd's of London. While his methods may seem a bit unorthodox, he gets the job done when needed, but not without a little something to learn or teach in the process. Through all of his adventures, some people call him a quack. Those who know him well call him a master of life...  ",
    "type": "OVA",
    "episodes": 15,
    "tags": [
        "adventure",
        "mystery"
    ],
    "released": "1999-12-21T02:00:00.000Z",
    "characters": [
        5899,
        112935,
        23417,
        23419,
        112165,
        23421
    ]
}