{
    "characters": [
        53241,
        53241,
        53243,
        53243,
        59771,
        59771,
        98679,
        98679,
        87841,
        87841,
        93015,
        93015,
        101515,
        101515,
        92995,
        92995,
        93075,
        93075,
        93077,
        93077,
        91125,
        91125,
        59773,
        59773,
        87843,
        87843,
        99781,
        99781,
        99455,
        99455,
        98675,
        98675,
        93011,
        93011,
        59775,
        59775,
        93067,
        93067,
        93069,
        93069,
        93065,
        93065,
        93003,
        93003,
        93089,
        93089,
        99779,
        99779,
        93059,
        93059,
        93013,
        93013,
        93063,
        93063,
        93073,
        93073,
        93057,
        93057,
        93061,
        93061,
        87847,
        87847,
        100111,
        100111,
        93007,
        93007,
        98677,
        98677,
        87839,
        87839,
        87851,
        87851,
        101517,
        101517,
        93001,
        93001,
        92997,
        92997,
        92107,
        92107,
        93019,
        93019,
        93005,
        93005,
        87845,
        87845,
        93053,
        93053,
        93049,
        93049,
        82731,
        82731,
        93033,
        93033,
        87849,
        87849,
        98673,
        98673,
        82755,
        82755
    ],
    "episodes": 11,
    "id": "19363",
    "picture": "http://cdn.myanimelist.net/images/anime/8/57995.jpg",
    "released": "2014-01-10T02:00:00.000Z",
    "synopsis": "As the new semester begins at Ooezo Agricultural High School, Hachiken is now used to the tough lifestyle of a rural, agricultural high school. While Hachiken still wonders what he will do in the future, he continues to discover both the harsh and the beautiful realities of the countryside.\n\n(Source: ANN)",
    "tags": [
        "comedy",
        "school",
        "shounen",
        "slice_of_life"
    ],
    "title": "Gin no Saji 2nd Season",
    "title_en": "Silver Spoon 2nd Season",
    "title_jp": "銀の匙",
    "type": "TV"
}