{
    "characters": [
        8946,
        8946,
        6356,
        6356,
        8945,
        8945,
        4003,
        4003,
        4368,
        4368,
        106407,
        106407,
        104671,
        104671,
        4004,
        4004,
        104663,
        104663,
        110591,
        110591,
        104597,
        104597,
        104661,
        104661,
        105657,
        105657,
        104601,
        104601,
        42159,
        42159,
        77359,
        77359,
        16557,
        16557,
        89435,
        89435,
        126724,
        126724,
        79901,
        79901,
        107903,
        107903,
        79629,
        79629,
        123053,
        123053,
        21962,
        21962,
        78409,
        78409,
        104595,
        104595,
        109003,
        109003
    ],
    "episodes": 24,
    "id": "20899",
    "picture": "http://cdn.myanimelist.net/images/anime/11/55267.jpg",
    "released": "2014-04-05T03:00:00.000Z",
    "synopsis": "In a Japanese jail sits 17-year-old Joutarou Kuujou: punk, fighter, delinquent...and possessed by a force beyond his control! Around the world, evil spirits are awakening: \"Stands,\" monstrous invisible creatures which give their bearers incredible powers. To save his mother's life, Joutarou must tame his dark forces and travel around the world to Cairo, Egypt, where a hundred-year-old vampire thirsts for the blood of his family. But the road is long, and an army of evil Stand Users wait to kill JoJo and his friends...\n\n(Source: VIZ Media)",
    "tags": [
        "action",
        "adventure",
        "shounen",
        "supernatural"
    ],
    "title": "JoJo no Kimyou na Bouken: Stardust Crusaders",
    "title_jp": "ジョジョの奇妙な冒険 スターダストクルセイダース",
    "type": "TV"
}