{
    "id": 2236,
    "title": "Toki wo Kakeru Shoujo",
    "title_en": "The Girl Who Leapt Through Time",
    "title_jp": "時をかける少女",
    "picture": "http://cdn.myanimelist.net/images/anime/1/2432.jpg",
    "synopsis": "The power to travel through time... It can be used for the good of humanity, or just selfishly abused. While many may fantasize about obtaining such a power, it has become nothing less than reality for otherwise-normal schoolgirl Konno Makoto.",
    "type": "Movie",
    "episodes": 1,
    "tags": [
        "adventure",
        "drama",
        "romance",
        "sci-fi"
    ],
    "released": "2006-07-15T03:00:00.000Z",
    "characters": [
        2530,
        2531,
        2532,
        16605,
        22928,
        16604,
        16631,
        28922,
        24227
    ]
}