{
    "id": 2402,
    "title": "Ashita no Joe",
    "title_en": "Tomorrow's Joe",
    "title_jp": "あしたのジョー",
    "picture": "http://cdn.myanimelist.net/images/anime/5/64671.jpg",
    "synopsis": "Joe, a teenage orphan in the slums of the Doya streets, meets Danpei, a homeless, alcoholic ex-boxing coach. Danpei, seeing Joe's boxing talent, decides to train him. When Joe is sent to a terrible juvenile home for petty crimes, he meets Rikiishi who becomes his boxing rival. Danpei arrives at the home to help Joe to train in order to defeat Rikiishi. When Joe decides to seriously pursue boxing, Danpei cannot get a coaching license because of his reputation as a drunk. ",
    "type": "TV",
    "episodes": 79,
    "tags": [
        "drama",
        "sports"
    ],
    "released": "1970-04-01T03:00:00.000Z",
    "characters": [
        46019,
        20185,
        11804,
        101933,
        59779,
        46055,
        46043,
        46053,
        76166,
        85465,
        76168,
        46051,
        121615
    ]
}