{
    "id": 2743,
    "title": "Mobile Suit Gundam Seed: Seed Supernova - Tanekyara Gekijou",
    "title_en": null,
    "title_jp": "たねきゃら劇場",
    "picture": "http://cdn.myanimelist.net/images/anime/3/52119.jpg",
    "synopsis": "The first two shorts feature the original Seed cast and deal with an attempt by Yzak Joule to reclaim his his honor from Athrun Zala after having been one-upped at seemingly every contest with him since his childhood. The last two shorts feature the Minerva crew sent back in time on comical missions from Gil in an attempt to disrupt key events of the Seed era with disastrous yet hilarious effect.",
    "type": "Special",
    "episodes": 4,
    "tags": [
        "comedy",
        "parody"
    ],
    "released": "2007-06-22T03:00:00.000Z",
    "characters": [
        117,
        115,
        116,
        123,
        120,
        1264,
        113,
        118,
        114,
        1340,
        121
    ]
}