{
    "characters": [
        324,
        324,
        327,
        327,
        330,
        330,
        332,
        332,
        329,
        329,
        328,
        328,
        331,
        331,
        326,
        326,
        325,
        325,
        5863,
        5863,
        20060,
        20060,
        3072,
        3072,
        16682,
        16682,
        11823,
        11823,
        5859,
        5859,
        19384,
        19384,
        6828,
        6828,
        5857,
        5857,
        36247,
        36247,
        6395,
        6395,
        2719,
        2719,
        6867,
        6867,
        2718,
        2718,
        36273,
        36273,
        36272,
        36272,
        52085,
        52085,
        5881,
        5881,
        3659,
        3659,
        5858,
        5858,
        43861,
        43861,
        5880,
        5880,
        5878,
        5878,
        5868,
        5868,
        5220,
        5220,
        16593,
        16593,
        11054,
        11054,
        9489,
        9489,
        2725,
        2725,
        4058,
        4058,
        5865,
        5865,
        6399,
        6399,
        5856,
        5856,
        3951,
        3951,
        31916,
        31916,
        5877,
        5877,
        5876,
        5876,
        5900,
        5900,
        19333,
        19333
    ],
    "episodes": 6,
    "id": "2752",
    "picture": "http://cdn.myanimelist.net/images/anime/10/3713.jpg",
    "released": "2007-06-22T03:00:00.000Z",
    "synopsis": "The tournament continues.",
    "tags": [
        "action",
        "comedy",
        "sports"
    ],
    "title": "Prince of Tennis: The National Tournament Semifinals",
    "title_jp": "テニスの王子様 全国大会篇 Semifinal",
    "type": "OVA"
}