{
    "characters": [
        2926,
        2926,
        758,
        758,
        1816,
        1816,
        456,
        456,
        21600,
        21600,
        36259,
        36259,
        4319,
        4319,
        757,
        757,
        2930,
        2930,
        2911,
        2911,
        2928,
        2928,
        107385,
        107385,
        11826,
        11826,
        2860,
        2860,
        2931,
        2931,
        2932,
        2932,
        18587,
        18587,
        4459,
        4459,
        18586,
        18586,
        2321,
        2321,
        2929,
        2929,
        2933,
        2933,
        2927,
        2927
    ],
    "episodes": 1,
    "id": "317",
    "picture": "http://cdn.myanimelist.net/images/anime/1/317.jpg",
    "released": "2005-09-14T03:00:00.000Z",
    "synopsis": "Two years after the end of Final Fantasy VII the world is starting to get back on it's feet and is working towards a new future. However, there is a new threat from a new illness called Geo-stigma, and three men that seem to be seeking Jenova. Cloud and his friends from the orginal game must once again reunite to combat the new threat.\n\n(Source: ANN)",
    "tags": [
        "action",
        "fantasy",
        "super_power"
    ],
    "title": "Final Fantasy VII: Advent Children",
    "title_jp": "ファイナルファンタジーVII アドベントチルドレン",
    "type": "Movie"
}