{
    "characters": [],
    "episodes": 23,
    "id": "4061",
    "picture": "http://cdn.myanimelist.net/images/anime/8/44608.jpg",
    "released": "1988-10-02T03:00:00.000Z",
    "synopsis": "Every episode is a stand-alone retelling of a different fairy or folk tale. Not all of them are based on the fairy tales collected by the Brothers Grimm.",
    "tags": [
        "adventure",
        "comedy",
        "fantasy",
        "kids",
        "magic"
    ],
    "title": "Grimm Masterpiece Theater II",
    "title_en": "Grimm's Fairy Tale Classics",
    "title_jp": "新グリム名作劇場",
    "type": "TV"
}