{
    "id": 4981,
    "title": "Casshern Sins",
    "title_en": null,
    "title_jp": "キャシャーン SINS",
    "picture": "http://cdn.myanimelist.net/images/anime/8/23336.jpg",
    "synopsis": "In the distant future, where cyborgs and humans struggle to survive after the war which destroyed the world, a being in white suit awakens. His name is Casshern and he remembers nothing of his own past. ",
    "type": "TV",
    "episodes": 24,
    "tags": [
        "action",
        "adventure",
        "drama",
        "psychological",
        "sci-fi"
    ],
    "released": "2008-10-02T03:00:00.000Z",
    "characters": [
        16181,
        16246,
        16197,
        16247,
        16450,
        17466,
        16198,
        16681,
        17699,
        17896,
        17252,
        17863,
        16196,
        16917,
        17078,
        18026,
        19187,
        17456,
        28498,
        16566,
        19188,
        95431
    ]
}