{
    "characters": [
        199,
        199,
        200,
        200,
        201,
        201,
        203,
        203,
        204,
        204,
        202,
        202,
        198,
        198,
        970,
        970,
        3177,
        3177,
        3176,
        3176,
        17802,
        17802,
        17185,
        17185,
        967,
        967,
        205,
        205,
        950,
        950,
        22494,
        22494,
        949,
        949,
        16980,
        16980,
        16977,
        16977,
        961,
        961,
        16979,
        16979,
        971,
        971,
        47303,
        47303,
        973,
        973,
        15570,
        15570,
        969,
        969,
        17183,
        17183,
        3175,
        3175,
        9140,
        9140,
        16895,
        16895,
        22491,
        22491,
        964,
        964,
        17182,
        17182,
        16978,
        16978,
        972,
        972,
        16896,
        16896,
        9430,
        9430
    ],
    "episodes": 2,
    "id": "517",
    "picture": "http://cdn.myanimelist.net/images/anime/5/75489.jpg",
    "released": "2005-12-22T02:00:00.000Z",
    "synopsis": "This two-part OVA is a series of shorts in relation to the School Rumble series. This OVA fills in gaps with new content between episodes from beginning to nearly the end.\n\n(Source: ANN)",
    "tags": [
        "comedy",
        "romance",
        "school",
        "shounen"
    ],
    "title": "School Rumble Ichi Gakki Hoshuu",
    "title_jp": "スクールランブル一学期補習",
    "type": "OVA"
}