{
    "id": 543,
    "title": "Vampire Hunter D (2000)",
    "title_en": "Vampire Hunter D: Bloodlust",
    "title_jp": "バンパイアハンターD",
    "picture": "http://cdn.myanimelist.net/images/anime/9/21432.jpg",
    "synopsis": "The story revolves around D, the infamous \"dunpeal\" (born of a vampire father and a human mother) outcast and renowned vampire hunter. His prowess at hunting the creatures of the night allowing his acceptance among humans, he is called upon to locate Charlotte Elbourne, the lovely daughter of an affluent family who has been mysteriously kidnapped.",
    "type": "Movie",
    "episodes": 1,
    "tags": [
        "action",
        "drama",
        "fantasy",
        "horror",
        "romance",
        "sci-fi",
        "vampire"
    ],
    "released": "2000-08-25T03:00:00.000Z",
    "characters": [
        1018,
        1028,
        1025,
        17925,
        1029,
        38719,
        38720,
        1022,
        1019,
        1020,
        1021,
        1026,
        1023,
        1024,
        1027,
        1030
    ]
}