{
    "id": 60,
    "title": "Chrno Crusade",
    "title_en": "Chrono Crusade",
    "title_jp": "クロノクルセイド",
    "picture": "http://cdn.myanimelist.net/images/anime/13/14141.jpg",
    "synopsis": "The year is 1928 A.D. The place is New York, U.S.A. The economic prosperity brought forth after the Great War also heightened the presence of something far darker and much more sinister: the demonic Sinners. The Magdalene Order is an organization that tries to counter this force. Two of its exorcists are Rosette Christopher and her assistant, Chrono. Both appear out of place in an organization like this, and they are in a quest to find Rosette's missing brother, Joshua. Their relationships, secrets and fates can only be revealed in time...",
    "type": "TV",
    "episodes": 24,
    "tags": [
        "action",
        "demons",
        "romance",
        "supernatural"
    ],
    "released": "2003-11-24T02:00:00.000Z",
    "characters": [
        2033,
        2034,
        2038,
        2036,
        2035,
        38023,
        2043,
        12565,
        17484,
        2045,
        5406,
        5236,
        2044,
        44048,
        2042,
        48217,
        5237,
        46847
    ]
}