{
    "characters": [
        33973,
        33973,
        33474,
        33474,
        24623,
        24623,
        46205,
        46205,
        77403,
        77403,
        46207,
        46207,
        46211,
        46211,
        125317,
        125317,
        35712,
        35712,
        112405,
        112405,
        111249,
        111249,
        46209,
        46209,
        136550,
        136550,
        24624,
        24624,
        50193,
        50193
    ],
    "episodes": 1,
    "id": "6675",
    "picture": "http://cdn.myanimelist.net/images/anime/9/34297.jpg",
    "released": "2009-08-14T03:00:00.000Z",
    "synopsis": "In a universe full of aliens, only one racer can be the best. Only one can win the greatest race in the entire galaxy, the Redline. This year’s Redline will be especially dangerous, as it will take place on the planet Roboworld with its trigger-happy military and criminals who look to turn the race to their own advantage.\n\nJP is one of the only humans who qualified to enter the Redline. Made popular by his refusal to put any weapons on his vehicle unlike most racers, he relies only on speed and his own unparalleled driving skills. At this race, JP runs into Sonoshee McLaren, a beautiful woman and the only other human that qualified for Redline. Amidst the dizzying speed and action of Redline, he will have to decide if she is just a rival, or something more.",
    "tags": [
        "action",
        "cars",
        "sci-fi",
        "sports"
    ],
    "title": "Redline",
    "title_en": "Redline",
    "title_jp": "REDLINE",
    "type": "Movie"
}