{
    "id": 6896,
    "title": "Pandora Hearts Specials",
    "title_en": null,
    "title_jp": "パンドラハーツ",
    "picture": "http://cdn.myanimelist.net/images/anime/13/21439.jpg",
    "synopsis": "Pandora Hearts DVD shorts.  ",
    "type": "Special",
    "episodes": 9,
    "tags": [
        "comedy"
    ],
    "released": "2009-07-24T03:00:00.000Z",
    "characters": [
        13836,
        16211,
        13835,
        19110,
        107909,
        14020,
        20609,
        20843,
        19583,
        21415,
        21105,
        17888,
        14021,
        19370,
        21111,
        21420
    ]
}