{
    "characters": [
        1336,
        1336,
        1335,
        1335,
        35015,
        35015,
        129507,
        129507,
        129559,
        129559,
        129508,
        129508,
        129509,
        129509,
        129510,
        129510,
        43138,
        43138,
        129532,
        129532,
        1349,
        1349,
        129514,
        129514,
        129541,
        129541,
        129511,
        129511,
        129513,
        129513,
        129553,
        129553,
        129515,
        129515,
        129557,
        129557,
        129516,
        129516,
        42320,
        42320,
        129517,
        129517,
        131043,
        131043,
        129518,
        129518,
        129519,
        129519,
        129522,
        129522,
        129523,
        129523,
        129525,
        129525,
        129527,
        129527,
        129528,
        129528,
        129524,
        129524,
        129529,
        129529,
        102655,
        102655,
        129530,
        129530,
        42329,
        42329,
        42328,
        42328,
        129551,
        129551,
        129531,
        129531,
        129533,
        129533,
        129534,
        129534,
        129535,
        129535,
        129536,
        129536,
        129537,
        129537,
        129520,
        129520,
        35018,
        35018,
        129549,
        129549,
        1340,
        1340,
        116491,
        116491,
        129538,
        129538,
        24770,
        24770,
        1350,
        1350,
        129540,
        129540,
        1339,
        1339,
        31333,
        31333,
        1384,
        1384,
        31331,
        31331,
        129543,
        129543,
        129544,
        129544,
        129542,
        129542,
        1351,
        1351,
        25455,
        25455,
        43118,
        43118,
        129545,
        129545,
        129546,
        129546,
        129547,
        129547,
        1338,
        1338,
        129550,
        129550,
        43152,
        43152,
        1337,
        1337,
        129564,
        129564,
        129552,
        129552,
        129554,
        129554,
        44647,
        44647,
        129555,
        129555,
        16282,
        16282,
        129548,
        129548,
        43117,
        43117,
        129539,
        129539,
        42319,
        42319,
        42318,
        42318,
        129556,
        129556,
        35017,
        35017,
        129558,
        129558,
        1342,
        1342,
        131012,
        131012,
        129560,
        129560,
        129561,
        129561,
        1386,
        1386,
        129562,
        129562,
        129563,
        129563,
        129565,
        129565,
        129566,
        129566,
        129567,
        129567,
        129568,
        129568,
        129570,
        129570,
        128835,
        128835,
        1352,
        1352,
        29686,
        29686,
        30965,
        30965,
        35019,
        35019,
        44645,
        44645,
        17498,
        17498,
        9497,
        9497,
        35020,
        35020,
        129571,
        129571
    ],
    "episodes": 43,
    "id": "80",
    "picture": "http://cdn.myanimelist.net/images/anime/5/12453.jpg",
    "released": "1979-04-07T03:00:00.000Z",
    "synopsis": "In the year Universal Century 0079, humanity lives in space colonies called Sides. Side 3, the Principality of Zeon, has declared war on the Earth Federation. After the initial fighting, an 8-month stalemate occurred. However that stalemate breaks when Amuro Ray stumbles upon the Gundam, the Earth Federation's secret weapon. Now Amuro and the crew of White Base must stand up to Zeon in order to end the war.\n\n(Source: ANN)",
    "tags": [
        "action",
        "mecha",
        "military",
        "sci-fi",
        "shounen",
        "space"
    ],
    "title": "Mobile Suit Gundam",
    "title_en": "Mobile Suit Gundam",
    "title_jp": "機動戦士ガンダム",
    "type": "TV"
}