{
    "id": 8022,
    "title": "Tegami Bachi Gakuen",
    "title_en": "Letter Bee Academy",
    "title_jp": "テガミバチ学園",
    "picture": "http://cdn.myanimelist.net/images/anime/4/19573.jpg",
    "synopsis": "Tegami Bachi specials.",
    "type": "Special",
    "episodes": 25,
    "tags": [
        "comedy"
    ],
    "released": "2010-01-27T02:00:00.000Z",
    "characters": [
        12517,
        14809,
        12511,
        14810,
        12519,
        43435,
        12518,
        12516,
        12509,
        43314,
        27402,
        24679,
        12512,
        12510,
        12513,
        43490
    ]
}