{
    "id": 8074,
    "title": "Highschool of the Dead",
    "title_en": "High School of the Dead",
    "title_jp": "学園黙示録 HIGHSCHOOL OF THE DEAD",
    "picture": "http://cdn.myanimelist.net/images/anime/11/78311.jpg",
    "synopsis": "A mysterious, lethal disease is on the loose worldwide, resulting in a catastrophic death rate of humanity, and the increasing rise of attacks, caused by the living dead.",
    "type": "TV",
    "episodes": 12,
    "tags": [
        "action",
        "ecchi",
        "horror",
        "supernatural"
    ],
    "released": "2010-07-05T03:00:00.000Z",
    "characters": [
        6043,
        6047,
        6045,
        25342,
        6046,
        6044,
        6048,
        34797,
        34799,
        19711,
        35070,
        37157,
        32736,
        35758,
        34798,
        35069,
        32744,
        37174,
        36381,
        36659,
        35757,
        34800,
        34801,
        42862,
        95947
    ]
}