{
    "characters": [
        382,
        382,
        381,
        381,
        379,
        379,
        383,
        383,
        380,
        380,
        378,
        378,
        4786,
        4786,
        12388,
        12388,
        55849,
        55849,
        55851,
        55851,
        10711,
        10711,
        17270,
        17270,
        30816,
        30816,
        31134,
        31134,
        31135,
        31135,
        30613,
        30613,
        13417,
        13417,
        14703,
        14703,
        10712,
        10712,
        10710,
        10710,
        17172,
        17172,
        30814,
        30814,
        8803,
        8803,
        30815,
        30815,
        14141,
        14141,
        30614,
        30614,
        30813,
        30813
    ],
    "episodes": 26,
    "id": "962",
    "picture": "http://cdn.myanimelist.net/images/anime/2/77621.jpg",
    "released": "2006-04-03T03:00:00.000Z",
    "synopsis": "Akari Mizunashi continues her training to become a Prima Undine (a professional tour guide gondolier) along with her friends Aika and Alice in the peaceful city of Neo Venezia. Despite the fact that these three girls are from competing companies, they are constantly together, learning more about how to become better tour guides and more about the mysteries of Neo Venezia.\n\nAs the group continues to meet interesting and unforgettable people through their daily routines, they will also come closer to the secrets that make the enigmatic and ever beautiful city of Neo Venezia so warm and alive.\n\nWelcome back to Neo Venezia: the city where miracles can be created by hand.\n\n[Written by MAL Rewrite]",
    "tags": [
        "fantasy",
        "sci-fi",
        "slice_of_life"
    ],
    "title": "Aria The Natural",
    "title_en": "Aria the Natural",
    "title_jp": "ARIA The NATURAL",
    "type": "TV"
}