{
    "id": 9760,
    "title": "Hoshi wo Ou Kodomo",
    "title_en": "Children who Chase Lost Voices",
    "title_jp": "星を追う子ども",
    "picture": "http://cdn.myanimelist.net/images/anime/4/29684.jpg",
    "synopsis": "Strange sounds in the darkness... Unearthly music from an old crystal radio... These are all the warning Asuna Watase has before a simple walk to her clubhouse catapults her into a nightmarish adventure that will take her beneath the Earth to a lost land beyond the realm of legend! Attacked by a strange monstrous creature, rescued by a mysterious stranger and pursued by a relentless enemy, Asuna finds herself enmeshed in a centuries old mystery that will bind her to a strange young defender and lead her inevitably, towards a secret that may hold the key to life itself! ",
    "type": "Movie",
    "episodes": 1,
    "tags": [
        "adventure",
        "fantasy",
        "romance"
    ],
    "released": "2011-05-07T03:00:00.000Z",
    "characters": [
        40077,
        39435,
        39434,
        42492,
        52851,
        52849,
        52847,
        52651,
        39436,
        52855,
        52853,
        52845
    ]
}